{"system_id":597188,"total_devices":24,"intervals":[{"end_at":"2019-10-07T07:10:00+11:00","devices_reporting":20,"powr":1,"enwh":0},{"end_at":"2019-10-07T07:15:00+11:00","devices_reporting":24,"powr":5,"enwh":0},{"end_at":"2019-10-07T07:20:00+11:00","devices_reporting":24,"powr":12,"enwh":1},{"end_at":"2019-10-07T07:25:00+11:00","devices_reporting":24,"powr":109,"enwh":9},{"end_at":"2019-10-07T07:30:00+11:00","devices_reporting":24,"powr":110,"enwh":9},{"end_at":"2019-10-07T07:35:00+11:00","devices_reporting":24,"powr":110,"enwh":9},{"end_at":"2019-10-07T07:40:00+11:00","devices_reporting":24,"powr":110,"enwh":9},{"end_at":"2019-10-07T07:45:00+11:00","devices_reporting":24,"powr":110,"enwh":9},{"end_at":"2019-10-07T07:50:00+11:00","devices_reporting":24,"powr":123,"enwh":10},{"end_at":"2019-10-07T07:55:00+11:00","devices_reporting":24,"powr":358,"enwh":30},{"end_at":"2019-10-07T08:00:00+11:00","devices_reporting":24,"powr":364,"enwh":30},{"end_at":"2019-10-07T08:05:00+11:00","devices_reporting":24,"powr":398,"enwh":33},{"end_at":"2019-10-07T08:10:00+11:00","devices_reporting":24,"powr":590,"enwh":49},{"end_at":"2019-10-07T08:15:00+11:00","devices_reporting":24,"powr":590,"enwh":49},{"end_at":"2019-10-07T08:20:00+11:00","devices_reporting":24,"powr":595,"enwh":50},{"end_at":"2019-10-07T08:25:00+11:00","devices_reporting":24,"powr":650,"enwh":54},{"end_at":"2019-10-07T08:30:00+11:00","devices_reporting":24,"powr":650,"enwh":54},{"end_at":"2019-10-07T08:35:00+11:00","devices_reporting":24,"powr":729,"enwh":61},{"end_at":"2019-10-07T08:40:00+11:00","devices_reporting":24,"powr":1288,"enwh":107},{"end_at":"2019-10-07T08:45:00+11:00","devices_reporting":24,"powr":1288,"enwh":107},{"end_at":"2019-10-07T08:50:00+11:00","devices_reporting":24,"powr":1310,"enwh":109},{"end_at":"2019-10-07T08:55:00+11:00","devices_reporting":24,"powr":1462,"enwh":122},{"end_at":"2019-10-07T09:00:00+11:00","devices_reporting":24,"powr":1462,"enwh":122},{"end_at":"2019-10-07T09:05:00+11:00","devices_reporting":24,"powr":1468,"enwh":122},{"end_at":"2019-10-07T09:10:00+11:00","devices_reporting":24,"powr":1549,"enwh":129},{"end_at":"2019-10-07T09:15:00+11:00","devices_reporting":24,"powr":1549,"enwh":129},{"end_at":"2019-10-07T09:20:00+11:00","devices_reporting":24,"powr":1599,"enwh":133},{"end_at":"2019-10-07T09:25:00+11:00","devices_reporting":24,"powr":2015,"enwh":168},{"end_at":"2019-10-07T09:30:00+11:00","devices_reporting":24,"powr":2015,"enwh":168},{"end_at":"2019-10-07T09:35:00+11:00","devices_reporting":24,"powr":2025,"enwh":169},{"end_at":"2019-10-07T09:40:00+11:00","devices_reporting":24,"powr":2218,"enwh":185},{"end_at":"2019-10-07T09:45:00+11:00","devices_reporting":24,"powr":2218,"enwh":185},{"end_at":"2019-10-07T09:50:00+11:00","devices_reporting":24,"powr":2314,"enwh":193},{"end_at":"2019-10-07T09:55:00+11:00","devices_reporting":24,"powr":3158,"enwh":263},{"end_at":"2019-10-07T10:00:00+11:00","devices_reporting":24,"powr":3158,"enwh":263},{"end_at":"2019-10-07T10:05:00+11:00","devices_reporting":24,"powr":3057,"enwh":255},{"end_at":"2019-10-07T10:10:00+11:00","devices_reporting":24,"powr":2355,"enwh":196},{"end_at":"2019-10-07T10:15:00+11:00","devices_reporting":24,"powr":2355,"enwh":196},{"end_at":"2019-10-07T10:20:00+11:00","devices_reporting":24,"powr":2370,"enwh":197},{"end_at":"2019-10-07T10:25:00+11:00","devices_reporting":24,"powr":2604,"enwh":217},{"end_at":"2019-10-07T10:30:00+11:00","devices_reporting":24,"powr":2604,"enwh":217},{"end_at":"2019-10-07T10:35:00+11:00","devices_reporting":24,"powr":2572,"enwh":214},{"end_at":"2019-10-07T10:40:00+11:00","devices_reporting":24,"powr":2426,"enwh":202},{"end_at":"2019-10-07T10:45:00+11:00","devices_reporting":24,"powr":2426,"enwh":202},{"end_at":"2019-10-07T10:50:00+11:00","devices_reporting":24,"powr":2405,"enwh":200},{"end_at":"2019-10-07T10:55:00+11:00","devices_reporting":24,"powr":2340,"enwh":195},{"end_at":"2019-10-07T11:00:00+11:00","devices_reporting":24,"powr":2340,"enwh":195},{"end_at":"2019-10-07T11:05:00+11:00","devices_reporting":24,"powr":2290,"enwh":191},{"end_at":"2019-10-07T11:10:00+11:00","devices_reporting":24,"powr":1903,"enwh":159},{"end_at":"2019-10-07T11:15:00+11:00","devices_reporting":24,"powr":1903,"enwh":159},{"end_at":"2019-10-07T11:20:00+11:00","devices_reporting":24,"powr":2051,"enwh":171},{"end_at":"2019-10-07T11:25:00+11:00","devices_reporting":24,"powr":3546,"enwh":295},{"end_at":"2019-10-07T11:30:00+11:00","devices_reporting":24,"powr":3546,"enwh":295},{"end_at":"2019-10-07T11:35:00+11:00","devices_reporting":24,"powr":3397,"enwh":283},{"end_at":"2019-10-07T11:40:00+11:00","devices_reporting":24,"powr":2044,"enwh":170},{"end_at":"2019-10-07T11:45:00+11:00","devices_reporting":24,"powr":2044,"enwh":170},{"end_at":"2019-10-07T11:50:00+11:00","devices_reporting":24,"powr":2075,"enwh":173},{"end_at":"2019-10-07T11:55:00+11:00","devices_reporting":24,"powr":2507,"enwh":209},{"end_at":"2019-10-07T12:00:00+11:00","devices_reporting":24,"powr":2508,"enwh":209},{"end_at":"2019-10-07T12:05:00+11:00","devices_reporting":24,"powr":2566,"enwh":214},{"end_at":"2019-10-07T12:10:00+11:00","devices_reporting":24,"powr":3384,"enwh":282},{"end_at":"2019-10-07T12:15:00+11:00","devices_reporting":24,"powr":3384,"enwh":282},{"end_at":"2019-10-07T12:20:00+11:00","devices_reporting":24,"powr":3387,"enwh":282},{"end_at":"2019-10-07T12:25:00+11:00","devices_reporting":24,"powr":3718,"enwh":310},{"end_at":"2019-10-07T12:30:00+11:00","devices_reporting":24,"powr":3718,"enwh":310},{"end_at":"2019-10-07T12:35:00+11:00","devices_reporting":24,"powr":3596,"enwh":300},{"end_at":"2019-10-07T12:40:00+11:00","devices_reporting":24,"powr":2064,"enwh":172},{"end_at":"2019-10-07T12:45:00+11:00","devices_reporting":24,"powr":2064,"enwh":172},{"end_at":"2019-10-07T12:50:00+11:00","devices_reporting":24,"powr":2149,"enwh":179},{"end_at":"2019-10-07T12:55:00+11:00","devices_reporting":24,"powr":3520,"enwh":293},{"end_at":"2019-10-07T13:00:00+11:00","devices_reporting":24,"powr":3520,"enwh":293},{"end_at":"2019-10-07T13:05:00+11:00","devices_reporting":24,"powr":3426,"enwh":285},{"end_at":"2019-10-07T13:10:00+11:00","devices_reporting":24,"powr":2319,"enwh":193},{"end_at":"2019-10-07T13:15:00+11:00","devices_reporting":24,"powr":2319,"enwh":193},{"end_at":"2019-10-07T13:20:00+11:00","devices_reporting":24,"powr":2328,"enwh":194},{"end_at":"2019-10-07T13:25:00+11:00","devices_reporting":24,"powr":2723,"enwh":227},{"end_at":"2019-10-07T13:30:00+11:00","devices_reporting":24,"powr":2723,"enwh":227},{"end_at":"2019-10-07T13:35:00+11:00","devices_reporting":24,"powr":2683,"enwh":224},{"end_at":"2019-10-07T13:40:00+11:00","devices_reporting":24,"powr":2131,"enwh":178},{"end_at":"2019-10-07T13:45:00+11:00","devices_reporting":24,"powr":2131,"enwh":178},{"end_at":"2019-10-07T13:50:00+11:00","devices_reporting":24,"powr":2152,"enwh":179},{"end_at":"2019-10-07T13:55:00+11:00","devices_reporting":24,"powr":2876,"enwh":240},{"end_at":"2019-10-07T14:00:00+11:00","devices_reporting":24,"powr":2876,"enwh":240},{"end_at":"2019-10-07T14:05:00+11:00","devices_reporting":24,"powr":2929,"enwh":244},{"end_at":"2019-10-07T14:10:00+11:00","devices_reporting":24,"powr":4636,"enwh":386},{"end_at":"2019-10-07T14:15:00+11:00","devices_reporting":24,"powr":4637,"enwh":386},{"end_at":"2019-10-07T14:20:00+11:00","devices_reporting":24,"powr":4571,"enwh":381},{"end_at":"2019-10-07T14:25:00+11:00","devices_reporting":24,"powr":3382,"enwh":282},{"end_at":"2019-10-07T14:30:00+11:00","devices_reporting":24,"powr":3384,"enwh":282},{"end_at":"2019-10-07T14:35:00+11:00","devices_reporting":24,"powr":3408,"enwh":284},{"end_at":"2019-10-07T14:40:00+11:00","devices_reporting":24,"powr":4772,"enwh":398},{"end_at":"2019-10-07T14:45:00+11:00","devices_reporting":24,"powr":4780,"enwh":398},{"end_at":"2019-10-07T14:50:00+11:00","devices_reporting":24,"powr":4741,"enwh":395},{"end_at":"2019-10-07T14:55:00+11:00","devices_reporting":24,"powr":3319,"enwh":277},{"end_at":"2019-10-07T15:00:00+11:00","devices_reporting":24,"powr":3322,"enwh":277},{"end_at":"2019-10-07T15:05:00+11:00","devices_reporting":24,"powr":3302,"enwh":275},{"end_at":"2019-10-07T15:10:00+11:00","devices_reporting":24,"powr":2762,"enwh":230},{"end_at":"2019-10-07T15:15:00+11:00","devices_reporting":24,"powr":2768,"enwh":231},{"end_at":"2019-10-07T15:20:00+11:00","devices_reporting":24,"powr":2758,"enwh":230},{"end_at":"2019-10-07T15:25:00+11:00","devices_reporting":24,"powr":2775,"enwh":231},{"end_at":"2019-10-07T15:30:00+11:00","devices_reporting":24,"powr":2791,"enwh":233},{"end_at":"2019-10-07T15:35:00+11:00","devices_reporting":24,"powr":2783,"enwh":232},{"end_at":"2019-10-07T15:40:00+11:00","devices_reporting":24,"powr":2187,"enwh":182},{"end_at":"2019-10-07T15:45:00+11:00","devices_reporting":24,"powr":2191,"enwh":183},{"end_at":"2019-10-07T15:50:00+11:00","devices_reporting":24,"powr":2189,"enwh":182},{"end_at":"2019-10-07T15:55:00+11:00","devices_reporting":24,"powr":1947,"enwh":162},{"end_at":"2019-10-07T16:00:00+11:00","devices_reporting":24,"powr":1952,"enwh":163},{"end_at":"2019-10-07T16:05:00+11:00","devices_reporting":24,"powr":1948,"enwh":162},{"end_at":"2019-10-07T16:10:00+11:00","devices_reporting":24,"powr":1668,"enwh":139},{"end_at":"2019-10-07T16:15:00+11:00","devices_reporting":24,"powr":1672,"enwh":139},{"end_at":"2019-10-07T16:20:00+11:00","devices_reporting":24,"powr":1676,"enwh":140},{"end_at":"2019-10-07T16:25:00+11:00","devices_reporting":24,"powr":2582,"enwh":215},{"end_at":"2019-10-07T16:30:00+11:00","devices_reporting":24,"powr":2608,"enwh":217},{"end_at":"2019-10-07T16:35:00+11:00","devices_reporting":24,"powr":2600,"enwh":217},{"end_at":"2019-10-07T16:40:00+11:00","devices_reporting":24,"powr":1157,"enwh":96},{"end_at":"2019-10-07T16:45:00+11:00","devices_reporting":24,"powr":1141,"enwh":95},{"end_at":"2019-10-07T16:50:00+11:00","devices_reporting":24,"powr":1139,"enwh":95},{"end_at":"2019-10-07T16:55:00+11:00","devices_reporting":24,"powr":618,"enwh":52},{"end_at":"2019-10-07T17:00:00+11:00","devices_reporting":24,"powr":610,"enwh":51},{"end_at":"2019-10-07T17:05:00+11:00","devices_reporting":24,"powr":610,"enwh":51},{"end_at":"2019-10-07T17:10:00+11:00","devices_reporting":24,"powr":633,"enwh":53},{"end_at":"2019-10-07T17:15:00+11:00","devices_reporting":24,"powr":637,"enwh":53},{"end_at":"2019-10-07T17:20:00+11:00","devices_reporting":24,"powr":638,"enwh":53},{"end_at":"2019-10-07T17:25:00+11:00","devices_reporting":24,"powr":1147,"enwh":96},{"end_at":"2019-10-07T17:30:00+11:00","devices_reporting":24,"powr":1170,"enwh":97},{"end_at":"2019-10-07T17:35:00+11:00","devices_reporting":24,"powr":1170,"enwh":97},{"end_at":"2019-10-07T17:40:00+11:00","devices_reporting":24,"powr":1054,"enwh":88},{"end_at":"2019-10-07T17:45:00+11:00","devices_reporting":24,"powr":1057,"enwh":88},{"end_at":"2019-10-07T17:50:00+11:00","devices_reporting":24,"powr":1057,"enwh":88},{"end_at":"2019-10-07T17:55:00+11:00","devices_reporting":24,"powr":791,"enwh":66},{"end_at":"2019-10-07T18:00:00+11:00","devices_reporting":24,"powr":781,"enwh":65},{"end_at":"2019-10-07T18:05:00+11:00","devices_reporting":24,"powr":781,"enwh":65},{"end_at":"2019-10-07T18:10:00+11:00","devices_reporting":24,"powr":403,"enwh":34},{"end_at":"2019-10-07T18:15:00+11:00","devices_reporting":24,"powr":387,"enwh":32},{"end_at":"2019-10-07T18:20:00+11:00","devices_reporting":24,"powr":387,"enwh":32},{"end_at":"2019-10-07T18:25:00+11:00","devices_reporting":24,"powr":486,"enwh":40},{"end_at":"2019-10-07T18:30:00+11:00","devices_reporting":24,"powr":495,"enwh":41},{"end_at":"2019-10-07T18:35:00+11:00","devices_reporting":24,"powr":495,"enwh":41},{"end_at":"2019-10-07T18:40:00+11:00","devices_reporting":24,"powr":604,"enwh":50},{"end_at":"2019-10-07T18:45:00+11:00","devices_reporting":24,"powr":613,"enwh":51},{"end_at":"2019-10-07T18:50:00+11:00","devices_reporting":24,"powr":613,"enwh":51},{"end_at":"2019-10-07T18:55:00+11:00","devices_reporting":24,"powr":290,"enwh":24},{"end_at":"2019-10-07T19:00:00+11:00","devices_reporting":24,"powr":269,"enwh":22},{"end_at":"2019-10-07T19:05:00+11:00","devices_reporting":24,"powr":269,"enwh":22},{"end_at":"2019-10-07T19:10:00+11:00","devices_reporting":24,"powr":164,"enwh":14},{"end_at":"2019-10-07T19:15:00+11:00","devices_reporting":24,"powr":156,"enwh":13},{"end_at":"2019-10-07T19:20:00+11:00","devices_reporting":24,"powr":156,"enwh":13},{"end_at":"2019-10-07T19:25:00+11:00","devices_reporting":24,"powr":11,"enwh":1}],"meta":{"status":"normal","last_report_at":"2020-03-24T19:39:38+11:00","last_energy_at":"2020-03-24T19:29:35+11:00","operational_at":"2015-04-07T17:00:00+10:00"}}